osfexport/__init__.py
osfexport/cli.py
osfexport/exporter.py
osfexport/formatter.py
osfexport/font/DejaVuSans-Bold.ttf
osfexport/font/DejaVuSans-BoldOblique.ttf
osfexport/font/DejaVuSans-Oblique.ttf
osfexport/font/DejaVuSans.ttf
osfexport/font/DejaVu_LICENSE.txt
osfexport/stubs/asingle.json
osfexport/stubs/contributorstubs.json
osfexport/stubs/custommetadatastub.json
osfexport/stubs/doistubs.json
osfexport/stubs/institutionstubs.json
osfexport/stubs/licensestub.json
osfexport/stubs/nodestubs.json
osfexport/stubs/nodestubs2.json
osfexport/stubs/singlenode.json
osfexport/stubs/subjectsstub.json
osfexport/stubs/components/empty-children.json
osfexport/stubs/components/x-child-1.json
osfexport/stubs/components/x-child-2.json
osfexport/stubs/files/rootfiles.json
osfexport/stubs/files/rootfolders.json
osfexport/stubs/files/tf1files.json
osfexport/stubs/files/tf1folders-2.json
osfexport/stubs/files/tf1folders.json
osfexport/stubs/files/tf2-second-files-2.json
osfexport/stubs/files/tf2-second-files.json
osfexport/stubs/files/tf2-second-folders.json
osfexport/stubs/files/tf2files.json
osfexport/stubs/files/tf2folders.json
osfexport/stubs/wikis/anotherone.md
osfexport/stubs/wikis/helloworld.md
osfexport/stubs/wikis/home.md
osfexport/stubs/wikis/wikis2stubs.json
osfexport/stubs/wikis/wikistubs.json
osfexport-1.0.1.dist-info/entry_points.txt
osfexport-1.0.1.dist-info/licenses/LICENSE
osfexport-1.0.1.dist-info/WHEEL
osfexport-1.0.1.dist-info/METADATA
osfexport-1.0.1.dist-info/RECORD
