Metadata-Version: 2.4
Name: osfexport
Version: 1.0.1
Summary: A package for exporting projects from the Open Science Framework web app. Comes with a command-line interface for exporting projects.
Keywords: OSF,osf,backup,Open Science Framework,export,Center for Open Science,COS,open science,archive
Author-email: Benito Matischen <benito.matischen@manchester.ac.uk>, Ramiro Bravo <ramiro.bravo@manchester.ac.uk>, Sarah Jaffa <sarah.jaffa@manchester.ac.uk>, Center for Open Science <contact@cos.io>
Requires-Python: >=3.12
License-Expression: Apache-2.0
Classifier: Programming Language :: Python :: 3.12
Classifier: Operating System :: OS Independent
Classifier: Development Status :: 5 - Production/Stable
Classifier: Environment :: Console
Classifier: Topic :: System :: Archiving :: Backup
License-File: LICENSE
Requires-Dist: click==8.2.1
Requires-Dist: fpdf2==2.8.3
Requires-Dist: pypdf==5.7.0
Requires-Dist: mistletoe==1.4.0
Requires-Dist: qrcode==8.2
Project-URL: Issues, https://github.com/CenterForOpenScience/osf-project-exporter/issues
Project-URL: ReleaseNotes, https://github.com/CenterForOpenScience/osf-project-exporter/releases
Project-URL: Repository, https://github.com/CenterForOpenScience/osf-project-exporter/tree/development
